{
    "menus": [
        {"name": "햄버거"},
        {"name": "샌드위치"},
        {"name": "피자"},
        {"name": "간장제육덮밥"},
        {"name": "김치볶음밥"},
        {"name": "뚝배기낙지덮밥"},
        {"name": "백반"},
        {"name": "점심뷔페"},
        {"name": "알밥"},
        {"name": "돌솥비빔밥"},
        {"name": "뚝배기제육덮밥"},
        {"name": "베트남식 볶음밥"},
        {"name": "태국식 볶음밥"},
        {"name": "연어덮밥"},
        {"name": "초밥"},
        {"name": "돈부리"},
        {"name": "회덮밥"},
        {"name": "짜장볶음밥"},
        {"name": "칼국수"},
        {"name": "라멘"},
        {"name": "김치우동"},
        {"name": "우동"},
        {"name": "잔치국수"},
        {"name": "비빔국수"},
        {"name": "짜장면"},
        {"name": "짬뽕"},
        {"name": "분짜"},
        {"name": "쌀국수"},
        {"name": "팟타이"},
        {"name": "모밀"},
        {"name": "냉면"},
        {"name": "파스타"},
        {"name": "국밥"},
        {"name": "감자탕"},
        {"name": "순두부찌개"},
        {"name": "알탕"},
        {"name": "부대찌개"},
        {"name": "김치찌개"},
        {"name": "갈비탕"},
        {"name": "곰탕"},
        {"name": "추어탕"},
        {"name": "차돌된장찌개"},
        {"name": "순대국밥"},
        {"name": "샤브샤브"},
        {"name": "콩나물국밥"},
        {"name": "청국장"},
        {"name": "설렁탕"},
        {"name": "삼계탕"},
        {"name": "닭볶음탕"},
        {"name": "만두국"},
        {"name": "콩비지찌개"},
        {"name": "마라탕"},
        {"name": "시래기"},
        {"name": "라면"},
        {"name": "라볶이"},
        {"name": "김밥"},
        {"name": "로제떡볶이"},
        {"name": "떡볶이"},
        {"name": "제육볶음"},
        {"name": "돈가스"},
        {"name": "닭갈비"},
        {"name": "쭈꾸미"},
        {"name": "고등어구이"},
        {"name": "불고기"},
        {"name": "갈치구이"},
        {"name": "갈치조림"},
        {"name": "마라샹궈"},
        {"name": "보쌈"}
    ]
}